pv_prompt/__init__.py
pv_prompt/async_prompt.py
pv_prompt/base_prompts.py
pv_prompt/discovery.py
pv_prompt/helpers.py
pv_prompt/hub.py
pv_prompt/print_output.py
pv_prompt/resource_cache.py
pv_prompt/scenes.py
pv_prompt/settings.py
pv_prompt/shades.py
pv_prompt/zero_conf.py
pv_prompt/dongle/__init__.py
pv_prompt/dongle/dongle.py
pv_prompt/dongle/nordic.py
pv_prompt/dongle/start.py
test/__init__.py
test/test_async_prompt.py
test/test_command_options.py
pv_prompt-1.10.1.dist-info/METADATA
pv_prompt-1.10.1.dist-info/WHEEL
pv_prompt-1.10.1.dist-info/entry_points.txt
pv_prompt-1.10.1.dist-info/top_level.txt
pv_prompt-1.10.1.dist-info/RECORD
