Metadata-Version: 2.1
Name: pv-prompt
Version: 1.10.1
Summary: PowerView shades toolkit
Home-page: https://github.com/sander76/pv_prompt
Author: Sander Teunissen
License: MIT
Platform: UNKNOWN
Classifier: License :: OSI Approved :: MIT License
Classifier: Programming Language :: Python
Classifier: Programming Language :: Python :: 3.5
Classifier: Programming Language :: Python :: 3.6
Classifier: Programming Language :: Python :: Implementation :: CPython
Classifier: Programming Language :: Python :: Implementation :: PyPy
Requires-Python: >=3.5.0
Requires-Dist: prompt-toolkit
Requires-Dist: aiopvapi (>=1.6.14)
Requires-Dist: pysmb
Requires-Dist: asyncdns2
Requires-Dist: pygments
Requires-Dist: pyserial
